pproxy/__doc__.py
pproxy/__init__.py
pproxy/__main__.py
pproxy/cipher.py
pproxy/cipherpy.py
pproxy/plugin.py
pproxy/proto.py
pproxy/server.py
pproxy/sysproxy.py
pproxy/verbose.py
pproxy-2.7.8.dist-info/LICENSE
pproxy-2.7.8.dist-info/METADATA
pproxy-2.7.8.dist-info/WHEEL
pproxy-2.7.8.dist-info/entry_points.txt
pproxy-2.7.8.dist-info/top_level.txt
pproxy-2.7.8.dist-info/RECORD
