Metadata-Version: 2.1
Name: pproxy
Version: 2.7.8
Summary: Proxy server that can tunnel among remote servers by regex rules.
Home-page: https://github.com/qwj/python-proxy
Author: Qian Wenjie
Author-email: qianwenjie@gmail.com
License: MIT
Keywords: proxy socks http shadowsocks shadowsocksr ssr redirect pf tunnel cipher ssl udp
Platform: UNKNOWN
Classifier: Development Status :: 5 - Production/Stable
Classifier: Environment :: Console
Classifier: Intended Audience :: Developers
Classifier: Natural Language :: English
Classifier: Topic :: Software Development :: Build Tools
Classifier: License :: OSI Approved :: MIT License
Classifier: Programming Language :: Python :: 3
Classifier: Programming Language :: Python :: 3.6
Classifier: Programming Language :: Python :: 3.7
Requires-Python: >=3.6
Provides-Extra: accelerated
Requires-Dist: pycryptodome (>=3.7.2) ; extra == 'accelerated'
Requires-Dist: uvloop (>=0.13.0) ; extra == 'accelerated'
Provides-Extra: daemon
Requires-Dist: python-daemon (>=2.2.3) ; extra == 'daemon'
Provides-Extra: quic
Requires-Dist: aioquic (>=0.9.7) ; extra == 'quic'
Provides-Extra: sshtunnel
Requires-Dist: asyncssh (>=2.5.0) ; extra == 'sshtunnel'
